tinysklearn/__init__.py
tinysklearn/clusters.py
tinysklearn/datasets.py
tinysklearn/decomposition.py
tinysklearn/linear_model.py
tinysklearn/metrics.py
tinysklearn/model_selection.py
tinysklearn/neighbors.py
tinysklearn/preprocessing.py
tinysklearn/tree.py
tinysklearn-0.0.1.dist-info/LICENSE
tinysklearn-0.0.1.dist-info/METADATA
tinysklearn-0.0.1.dist-info/WHEEL
tinysklearn-0.0.1.dist-info/top_level.txt
tinysklearn-0.0.1.dist-info/RECORD
