Metadata-Version: 2.1
Name: tinysklearn
Version: 0.0.1
Summary: A small machine learning package, which can help people learn ML more easier
Home-page: https://github.com/pypa/sampleproject
Author: lyh
Author-email: 412929473@qq.com
License: UNKNOWN
Platform: UNKNOWN
Classifier: Programming Language :: Python :: 3
Classifier: License :: OSI Approved :: MIT License
Classifier: Operating System :: OS Independent
